odoo/addons/pos_user_restriction/README.rst
odoo/addons/pos_user_restriction/__init__.py
odoo/addons/pos_user_restriction/__manifest__.py
odoo/addons/pos_user_restriction/i18n/es.po
odoo/addons/pos_user_restriction/i18n/it.po
odoo/addons/pos_user_restriction/i18n/pos_user_restriction.pot
odoo/addons/pos_user_restriction/models/__init__.py
odoo/addons/pos_user_restriction/models/pos_config.py
odoo/addons/pos_user_restriction/models/pos_session.py
odoo/addons/pos_user_restriction/models/res_users.py
odoo/addons/pos_user_restriction/readme/CONFIGURE.md
odoo/addons/pos_user_restriction/readme/CONTRIBUTORS.md
odoo/addons/pos_user_restriction/readme/DESCRIPTION.md
odoo/addons/pos_user_restriction/readme/ROADMAP.md
odoo/addons/pos_user_restriction/security/ir.model.access.csv
odoo/addons/pos_user_restriction/security/pos_security.xml
odoo/addons/pos_user_restriction/static/description/icon.png
odoo/addons/pos_user_restriction/static/description/index.html
odoo/addons/pos_user_restriction/tests/__init__.py
odoo/addons/pos_user_restriction/tests/test_hacks.py
odoo/addons/pos_user_restriction/tests/test_pos_user_restriction.py
odoo/addons/pos_user_restriction/views/point_of_sale_views.xml
odoo/addons/pos_user_restriction/views/pos_config_views.xml
odoo_addon_pos_user_restriction-17.0.1.0.1.dist-info/METADATA
odoo_addon_pos_user_restriction-17.0.1.0.1.dist-info/WHEEL
odoo_addon_pos_user_restriction-17.0.1.0.1.dist-info/top_level.txt
odoo_addon_pos_user_restriction-17.0.1.0.1.dist-info/RECORD
