Metadata-Version: 2.1
Name: odoo-addon-pos_user_restriction
Version: 17.0.1.0.1
Requires-Python: >=3.10
Requires-Dist: odoo>=17.0a,<17.1dev
Summary: Restrict some users to see and use only certain points of sale
Home-page: https://github.com/OCA/pos
License: LGPL-3
Author: TAKOBI, Odoo Community Association (OCA)
Author-email: support@odoo-community.org
Classifier: Programming Language :: Python
Classifier: Framework :: Odoo
Classifier: Framework :: Odoo :: 17.0
Classifier: License :: OSI Approved :: GNU Lesser General Public License v3 (LGPLv3)
Classifier: Development Status :: 4 - Beta
